{
	"partitions" : [
		{
			"name" : "Top",
			"pins" : [
				{
					"name" : "tri_buf_en[0]",
					"strict" : false
				},
				{
					"name" : "tri_buf_en[1]",
					"strict" : false
				},
				{
					"name" : "tri_buf_en[2]",
					"strict" : false
				},
				{
					"name" : "tri_buf_en[3]",
					"strict" : false
				},
				{
					"name" : "Y",
					"strict" : false
				},
				{
					"name" : "S[1]",
					"strict" : false
				},
				{
					"name" : "S[0]",
					"strict" : false
				},
				{
					"name" : "E",
					"strict" : false
				},
				{
					"name" : "I[3]",
					"strict" : false
				},
				{
					"name" : "I[0]",
					"strict" : false
				},
				{
					"name" : "I[1]",
					"strict" : false
				},
				{
					"name" : "I[2]",
					"strict" : false
				}
			]
		}
	]
}